LICENSE
MANIFEST.in
README.md
setup.py
pypiup/__init__.py
pypiup/cli.py
pypiup/requirement.py
pypiup/requirements.py
pypiup.egg-info/PKG-INFO
pypiup.egg-info/SOURCES.txt
pypiup.egg-info/dependency_links.txt
pypiup.egg-info/entry_points.txt
pypiup.egg-info/requires.txt
pypiup.egg-info/top_level.txt
tests/__init__.py
tests/mocks.py
tests/test_cli.py