Metadata-Version: 1.1
Name: pypiup
Version: 0.0.2
Summary: Check whether your PyPI requirements are up to date.
Home-page: https://github.com/ekonstantinidis/pypiup
Author: Emmanouil Konstantinidis
Author-email: manos@iamemmanouil.com
License: BSD
Platform: UNKNOWN
Classifier: Development Status :: 5 - Production/Stable
Classifier: Environment :: Console
Classifier: Intended Audience :: Developers
Classifier: License :: OSI Approved :: BSD License
Classifier: Operating System :: OS Independent
Classifier: Programming Language :: Python
Classifier: Programming Language :: Python :: 2.7
Classifier: Programming Language :: Python :: 3
Classifier: Programming Language :: Python :: 3.4
Classifier: Programming Language :: Python :: 3.5
